README.md
setup.py
entry_logger_sanic/__init__.py
entry_logger_sanic/logger.py
entry_logger_sanic.egg-info/PKG-INFO
entry_logger_sanic.egg-info/SOURCES.txt
entry_logger_sanic.egg-info/dependency_links.txt
entry_logger_sanic.egg-info/not-zip-safe
entry_logger_sanic.egg-info/requires.txt
entry_logger_sanic.egg-info/top_level.txt