Metadata-Version: 2.1
Name: entry-logger-sanic
Version: 0.1.6
Summary: NDJSON formatted logger integration with Sanic
Home-page: https://github.com/EntryDSM/entry-logger-sanic
Author: NovemberOscar
Author-email: kim@seonghyeon.dev
License: MIT
Keywords: sanic,log,logger
Platform: any
Classifier: Development Status :: 3 - Alpha
Classifier: Environment :: Web Environment
Classifier: Intended Audience :: Developers
Classifier: License :: OSI Approved :: MIT License
Classifier: Operating System :: OS Independent
Classifier: Programming Language :: Python :: 3.6
Classifier: Programming Language :: Python :: 3.7
Classifier: Topic :: Internet :: WWW/HTTP :: Dynamic Content
Classifier: Topic :: Software Development :: Libraries :: Python Modules
